greff/__init__.py
greff/client.py
greff/field.py
greff/functions.py
greff/query.py
greff/type.py
greff/types.py
greff/typing.py
greff-0.0.1.dist-info/METADATA
greff-0.0.1.dist-info/WHEEL
greff-0.0.1.dist-info/RECORD
