Metadata-Version: 2.1
Name: greff
Version: 0.0.1
Summary: 
Author: daniel sonbolian
Author-email: dsal3389@gmail.com
Requires-Python: >=3.11,<4.0
Classifier: Programming Language :: Python :: 3
Classifier: Programming Language :: Python :: 3.11
